solarsynth/__init__.py
solarsynth/synth1.py
solarsynth/synth2.py
solarsynth-0.1.2.dist-info/METADATA
solarsynth-0.1.2.dist-info/WHEEL
solarsynth-0.1.2.dist-info/top_level.txt
solarsynth-0.1.2.dist-info/RECORD
