Metadata-Version: 2.4
Name: solarsynth
Version: 0.1.2
Summary: Add your description here
Requires-Python: >=3.13
Requires-Dist: numpy>=2.3.4
Requires-Dist: pandas>=2.3.3
Requires-Dist: pytest>=9.0.1
